{
  "metadata": {
    "session_id": "webapp_session_2025-12-19T02_08_22_359Z",
    "total_frames_processed": 40,
    "best_frames_saved": 10,
    "session_completed": "2025-12-19 02:08:31",
    "scoring_criteria": {
      "pose_weight": 0.6,
      "size_weight": 0.3,
      "position_weight": 0.1
    },
    "scoring_description": {
      "pose": "Frontality quality (pitch, yaw, roll) - TOP PRIORITY",
      "size": "Face size (prefers LARGER faces 30-45% of frame)",
      "position": "Face centering (both horizontal and vertical)"
    }
  },
  "frames": [
    {
      "filename": "frame_01.jpg",
      "rank": 1,
      "total_score": 95.33,
      "timestamp": 1766110106.4338465,
      "pose": {
        "pitch": -1.9,
        "yaw": -1.86,
        "roll": -178.85
      },
      "face_bbox": {
        "x_min": 71,
        "x_max": 439,
        "y_min": 281,
        "y_max": 721
      },
      "score_breakdown": {
        "pose_score": 94.77,
        "size_score": 100,
        "position_score": 84.63,
        "face_ratio": 0.419,
        "center_distance_x": 0.1025,
        "center_distance_y": 0.2049,
        "total_center_distance": 0.1537
      }
    },
    {
      "filename": "frame_02.jpg",
      "rank": 2,
      "total_score": 95.24,
      "timestamp": 1766110106.4012551,
      "pose": {
        "pitch": -0.62,
        "yaw": -2.38,
        "roll": -177.68
      },
      "face_bbox": {
        "x_min": 63,
        "x_max": 428,
        "y_min": 279,
        "y_max": 713
      },
      "score_breakdown": {
        "pose_score": 94.2,
        "size_score": 100,
        "position_score": 87.23,
        "face_ratio": 0.4099,
        "center_distance_x": 0.061,
        "center_distance_y": 0.1944,
        "total_center_distance": 0.1277
      }
    },
    {
      "filename": "frame_03.jpg",
      "rank": 3,
      "total_score": 94.13,
      "timestamp": 1766110106.5263364,
      "pose": {
        "pitch": -4.05,
        "yaw": -1.49,
        "roll": -178.03
      },
      "face_bbox": {
        "x_min": 74,
        "x_max": 448,
        "y_min": 285,
        "y_max": 729
      },
      "score_breakdown": {
        "pose_score": 93.11,
        "size_score": 100,
        "position_score": 82.65,
        "face_ratio": 0.4295,
        "center_distance_x": 0.127,
        "center_distance_y": 0.22,
        "total_center_distance": 0.1735
      }
    },
    {
      "filename": "frame_04.jpg",
      "rank": 4,
      "total_score": 94.08,
      "timestamp": 1766110106.2591884,
      "pose": {
        "pitch": 2.74,
        "yaw": -2.59,
        "roll": -177.02
      },
      "face_bbox": {
        "x_min": 49,
        "x_max": 413,
        "y_min": 280,
        "y_max": 711
      },
      "score_breakdown": {
        "pose_score": 91.76,
        "size_score": 100,
        "position_score": 90.25,
        "face_ratio": 0.4073,
        "center_distance_x": 0.002,
        "center_distance_y": 0.1931,
        "total_center_distance": 0.0975
      }
    },
    {
      "filename": "frame_05.jpg",
      "rank": 5,
      "total_score": 91.92,
      "timestamp": 1766110106.5991166,
      "pose": {
        "pitch": -8.65,
        "yaw": -1.15,
        "roll": -177.72
      },
      "face_bbox": {
        "x_min": 81,
        "x_max": 457,
        "y_min": 288,
        "y_max": 733
      },
      "score_breakdown": {
        "pose_score": 89.77,
        "size_score": 100,
        "position_score": 80.54,
        "face_ratio": 0.4333,
        "center_distance_x": 0.1611,
        "center_distance_y": 0.2281,
        "total_center_distance": 0.1946
      }
    },
    {
      "filename": "frame_06.jpg",
      "rank": 6,
      "total_score": 91.76,
      "timestamp": 1766110106.2068481,
      "pose": {
        "pitch": 6.63,
        "yaw": -2.65,
        "roll": -176.86
      },
      "face_bbox": {
        "x_min": 35,
        "x_max": 396,
        "y_min": 284,
        "y_max": 707
      },
      "score_breakdown": {
        "pose_score": 88.44,
        "size_score": 100,
        "position_score": 86.95,
        "face_ratio": 0.3957,
        "center_distance_x": 0.0694,
        "center_distance_y": 0.1916,
        "total_center_distance": 0.1305
      }
    },
    {
      "filename": "frame_07.jpg",
      "rank": 7,
      "total_score": 91.3,
      "timestamp": 1766110107.2877722,
      "pose": {
        "pitch": -9.93,
        "yaw": -0.73,
        "roll": -177.74
      },
      "face_bbox": {
        "x_min": 119,
        "x_max": 464,
        "y_min": 271,
        "y_max": 738
      },
      "score_breakdown": {
        "pose_score": 89.43,
        "size_score": 100,
        "position_score": 76.47,
        "face_ratio": 0.4177,
        "center_distance_x": 0.2571,
        "center_distance_y": 0.2136,
        "total_center_distance": 0.2353
      }
    },
    {
      "filename": "frame_08.jpg",
      "rank": 8,
      "total_score": 91.15,
      "timestamp": 1766110106.8735857,
      "pose": {
        "pitch": -10.49,
        "yaw": -0.76,
        "roll": -177.62
      },
      "face_bbox": {
        "x_min": 96,
        "x_max": 464,
        "y_min": 284,
        "y_max": 735
      },
      "score_breakdown": {
        "pose_score": 88.86,
        "size_score": 100,
        "position_score": 78.33,
        "face_ratio": 0.43,
        "center_distance_x": 0.207,
        "center_distance_y": 0.2263,
        "total_center_distance": 0.2167
      }
    },
    {
      "filename": "frame_09.jpg",
      "rank": 9,
      "total_score": 91.14,
      "timestamp": 1766110106.6958115,
      "pose": {
        "pitch": -10.66,
        "yaw": -0.81,
        "roll": -177.71
      },
      "face_bbox": {
        "x_min": 86,
        "x_max": 464,
        "y_min": 287,
        "y_max": 734
      },
      "score_breakdown": {
        "pose_score": 88.7,
        "size_score": 100,
        "position_score": 79.18,
        "face_ratio": 0.4368,
        "center_distance_x": 0.187,
        "center_distance_y": 0.2294,
        "total_center_distance": 0.2082
      }
    },
    {
      "filename": "frame_10.jpg",
      "rank": 10,
      "total_score": 90.69,
      "timestamp": 1766110107.1029377,
      "pose": {
        "pitch": -11.26,
        "yaw": -0.74,
        "roll": -177.54
      },
      "face_bbox": {
        "x_min": 106,
        "x_max": 464,
        "y_min": 279,
        "y_max": 736
      },
      "score_breakdown": {
        "pose_score": 88.23,
        "size_score": 100,
        "position_score": 77.52,
        "face_ratio": 0.4232,
        "center_distance_x": 0.2293,
        "center_distance_y": 0.2202,
        "total_center_distance": 0.2248
      }
    }
  ]
}